plover_application_controls/__init__.py
plover_application_controls/command.py
plover_application_controls/extension.py
plover_application_controls/meta.py
plover_application_controls/pywinctl/__init__.py
plover_application_controls/pywinctl/fake_tk.py
plover_application_controls/pywinctl/get.py
plover_application_controls/window/__init__.py
plover_application_controls/window/details.py
plover_application_controls/window/history.py
plover_application_controls/window/tracker.py
plover_application_controls-1.2.1.dist-info/LICENSE
plover_application_controls-1.2.1.dist-info/METADATA
plover_application_controls-1.2.1.dist-info/WHEEL
plover_application_controls-1.2.1.dist-info/entry_points.txt
plover_application_controls-1.2.1.dist-info/top_level.txt
plover_application_controls-1.2.1.dist-info/zip-safe
plover_application_controls-1.2.1.dist-info/RECORD
