Metadata-Version: 2.1
Name: plover-application-controls
Version: 1.2.1
Summary: Plover plugin to monitor and control the currently active window and switch between windows quickly
Home-page: https://github.com/Pipatooa/plover-application-controls
Author: Pipatooa
Author-email: pipatooa@pipatooa.co.uk
Keywords: plover plover_plugin
Requires-Python: >=3.7
License-File: LICENSE
Requires-Dist: plover (>=4.0.0dev12)
Requires-Dist: PyWinCtl (>=0.0.43)
